streamgrid/__init__.py
streamgrid/analytics.py
streamgrid/grid.py
streamgrid/plotting.py
streamgrid/stream.py
streamgrid/utils.py
streamgrid-1.0.10.dist-info/LICENSE
streamgrid-1.0.10.dist-info/METADATA
streamgrid-1.0.10.dist-info/WHEEL
streamgrid-1.0.10.dist-info/entry_points.txt
streamgrid-1.0.10.dist-info/top_level.txt
streamgrid-1.0.10.dist-info/RECORD
