Metadata-Version: 2.1
Name: streamgrid
Version: 1.0.10
Summary: Ultra-fast multi-stream: Display multiple video sources with object detection simultaneously using the CPU or GPU device.
Author: Muhammad Rizwan Munawar
Maintainer: Muhammad Rizwan Munawar
Project-URL: Homepage, https://github.com/RizwanMunawar/streamgrid
Project-URL: Repository, https://github.com/RizwanMunawar/streamgrid
Project-URL: Issues, https://github.com/RizwanMunawar/streamgrid/issues
Project-URL: Documentation, https://github.com/RizwanMunawar/streamgrid#readme
Keywords: video,streaming,display,multi-stream,opencv,real-time,python,ultralytics
Classifier: Development Status :: 4 - Beta
Classifier: Intended Audience :: Developers
Classifier: Intended Audience :: Education
Classifier: Intended Audience :: Science/Research
Classifier: Operating System :: OS Independent
Classifier: Programming Language :: Python :: 3
Classifier: Programming Language :: Python :: 3.8
Classifier: Programming Language :: Python :: 3.9
Classifier: Programming Language :: Python :: 3.10
Classifier: Programming Language :: Python :: 3.11
Classifier: Programming Language :: Python :: 3.12
Classifier: Topic :: Software Development
Classifier: Topic :: Scientific/Engineering
Classifier: Topic :: Multimedia :: Video :: Display
Classifier: Topic :: Software Development :: Libraries :: Python Modules
Classifier: Operating System :: POSIX :: Linux
Classifier: Operating System :: MacOS
Classifier: Operating System :: Microsoft :: Windows
Requires-Python: >=3.8
License-File: LICENSE
Requires-Dist: ultralytics
Requires-Dist: tqdm
